canlib/__about__.py
canlib/__init__.py
canlib/__version__.py
canlib/cenum.py
canlib/deprecation.py
canlib/device.py
canlib/dllLoader.py
canlib/ean.py
canlib/exceptions.py
canlib/frame.py
canlib/futureapi.py
canlib/j1939.py
canlib/kvDevice.py
canlib/kvMemoConfig.py
canlib/kvMessage.py
canlib/kvaMemoLibXml.py
canlib/versionnumber.py
canlib/canlib/__init__.py
canlib/canlib/_channel.py
canlib/canlib/busparams.py
canlib/canlib/channel.py
canlib/canlib/channeldata.py
canlib/canlib/constants.py
canlib/canlib/dll.py
canlib/canlib/enums.py
canlib/canlib/envvar.py
canlib/canlib/exceptions.py
canlib/canlib/iocontrol.py
canlib/canlib/iopin.py
canlib/canlib/objbuf.py
canlib/canlib/structures.py
canlib/canlib/timedomain.py
canlib/canlib/txe.py
canlib/canlib/wrapper.py
canlib/kvadblib/__init__.py
canlib/kvadblib/attribute.py
canlib/kvadblib/attributedef.py
canlib/kvadblib/bound_message.py
canlib/kvadblib/bound_signal.py
canlib/kvadblib/constants.py
canlib/kvadblib/dbc.py
canlib/kvadblib/dll.py
canlib/kvadblib/enums.py
canlib/kvadblib/exceptions.py
canlib/kvadblib/framebox.py
canlib/kvadblib/message.py
canlib/kvadblib/node.py
canlib/kvadblib/signal.py
canlib/kvadblib/wrapper.py
canlib/kvamemolibxml/__init__.py
canlib/kvamemolibxml/configuration.py
canlib/kvamemolibxml/constants.py
canlib/kvamemolibxml/dll.py
canlib/kvamemolibxml/enums.py
canlib/kvamemolibxml/exceptions.py
canlib/kvamemolibxml/wrapper.py
canlib/kvlclib/__init__.py
canlib/kvlclib/constants.py
canlib/kvlclib/converter.py
canlib/kvlclib/deprecated.py
canlib/kvlclib/dll.py
canlib/kvlclib/enums.py
canlib/kvlclib/exceptions.py
canlib/kvlclib/properties.py
canlib/kvlclib/readerformat.py
canlib/kvlclib/wrapper.py
canlib/kvlclib/writerformat.py
canlib/kvmlib/__init__.py
canlib/kvmlib/constants.py
canlib/kvmlib/deprecated.py
canlib/kvmlib/dll.py
canlib/kvmlib/enums.py
canlib/kvmlib/events.py
canlib/kvmlib/exceptions.py
canlib/kvmlib/kme.py
canlib/kvmlib/kmf.py
canlib/kvmlib/log.py
canlib/kvmlib/logfile.py
canlib-1.31.107.dist-info/LICENSE
canlib-1.31.107.dist-info/METADATA
canlib-1.31.107.dist-info/WHEEL
canlib-1.31.107.dist-info/top_level.txt
canlib-1.31.107.dist-info/RECORD
