Metadata-Version: 2.1
Name: canlib
Version: 1.31.107
Summary: Python wrapper for Kvaser CANlib
Home-page: https://github.com/Kvaser/pycanlib
Author: Kvaser AB
Author-email: support@kvaser.com
License: MIT
Keywords: development
Classifier: Development Status :: 4 - Beta
Classifier: Intended Audience :: Developers
Classifier: Topic :: Software Development
Classifier: License :: OSI Approved :: MIT License
Classifier: Programming Language :: Python :: 3.6
Classifier: Programming Language :: Python :: 3.7
Classifier: Programming Language :: Python :: 3.8
Classifier: Programming Language :: Python :: 3.9
Classifier: Programming Language :: Python :: 3.10
License-File: LICENSE
Requires-Dist: pydantic >=1.8.1
Provides-Extra: dev
Requires-Dist: pytest >=3.3.0 ; extra == 'dev'
Requires-Dist: pytest-cov >=2.5.1 ; extra == 'dev'
Requires-Dist: sphinx >=1.6.5 ; extra == 'dev'
Requires-Dist: sphinx-rtd-theme >=0.2.4 ; extra == 'dev'
Provides-Extra: test
Requires-Dist: pytest >=3.3.0 ; extra == 'test'
Requires-Dist: pandas >=1.2.3 ; extra == 'test'
